{
  "test_id": "7b8d4f9c-3a21-4e65-8b1a-9f0c2d3e4a5b",
  "correct": 14,
  "total": 20,
  "answered": 20,
  "pct": 70,
  "finished": false,
  "answers": [
    {
      "chosen": "A",
      "correct": true,
      "skipped": false
    },
    {
      "chosen": "B",
      "correct": true,
      "skipped": false
    },
    {
      "chosen": "C",
      "correct": true,
      "skipped": false
    },
    {
      "chosen": "D",
      "correct": true,
      "skipped": false
    },
    {
      "chosen": "A",
      "correct": false,
      "skipped": false
    },
    {
      "chosen": "A",
      "correct": true,
      "skipped": false
    },
    {
      "chosen": "B",
      "correct": true,
      "skipped": false
    },
    {
      "chosen": "C",
      "correct": true,
      "skipped": false
    },
    {
      "chosen": "D",
      "correct": true,
      "skipped": false
    },
    {
      "chosen": "E",
      "correct": true,
      "skipped": false
    },
    {
      "chosen": "A",
      "correct": true,
      "skipped": false
    },
    {
      "chosen": "B",
      "correct": true,
      "skipped": false
    },
    {
      "chosen": "B",
      "correct": false,
      "skipped": false
    },
    {
      "chosen": "C",
      "correct": false,
      "skipped": false
    },
    {
      "chosen": "A",
      "correct": false,
      "skipped": false
    },
    {
      "chosen": "E",
      "correct": false,
      "skipped": false
    },
    {
      "chosen": "B",
      "correct": true,
      "skipped": false
    },
    {
      "chosen": "C",
      "correct": true,
      "skipped": false
    },
    {
      "chosen": "C",
      "correct": false,
      "skipped": false
    },
    {
      "chosen": "E",
      "correct": true,
      "skipped": false
    }
  ],
  "date": "2026-05-28T01:03:19.019Z"
}