{
  "test_id": "e9b251cc-9d47-4f68-a7be-3214a1a8c549",
  "correct": 0,
  "total": 20,
  "answered": 0,
  "pct": 0,
  "finished": false,
  "answers": [
    {
      "chosen": null,
      "correct": false,
      "skipped": true
    },
    {
      "chosen": null,
      "correct": false,
      "skipped": true
    },
    {
      "chosen": null,
      "correct": false,
      "skipped": true
    },
    {
      "chosen": null,
      "correct": false,
      "skipped": true
    },
    {
      "chosen": null,
      "correct": false,
      "skipped": true
    },
    {
      "chosen": null,
      "correct": false,
      "skipped": true
    },
    {
      "chosen": null,
      "correct": false,
      "skipped": true
    },
    {
      "chosen": null,
      "correct": false,
      "skipped": true
    },
    {
      "chosen": null,
      "correct": false,
      "skipped": true
    },
    {
      "chosen": null,
      "correct": false,
      "skipped": true
    },
    {
      "chosen": null,
      "correct": false,
      "skipped": true
    },
    {
      "chosen": null,
      "correct": false,
      "skipped": true
    },
    {
      "chosen": null,
      "correct": false,
      "skipped": true
    },
    {
      "chosen": null,
      "correct": false,
      "skipped": true
    },
    {
      "chosen": null,
      "correct": false,
      "skipped": true
    },
    {
      "chosen": null,
      "correct": false,
      "skipped": true
    },
    {
      "chosen": null,
      "correct": false,
      "skipped": true
    },
    {
      "chosen": null,
      "correct": false,
      "skipped": true
    },
    {
      "chosen": null,
      "correct": false,
      "skipped": true
    },
    {
      "chosen": null,
      "correct": false,
      "skipped": true
    }
  ],
  "date": "2026-05-25T02:02:48.402Z"
}