{
  "test_id": "f5a8b2c4-9012-4d3e-a891-b67c4f1d8a90",
  "correct": 0,
  "total": 20,
  "answered": 0,
  "pct": 0,
  "finished": false,
  "answers": [
    {
      "chosen": null,
      "correct": false,
      "skipped": true
    },
    {
      "chosen": null,
      "correct": false,
      "skipped": true
    },
    {
      "chosen": null,
      "correct": false,
      "skipped": true
    },
    {
      "chosen": null,
      "correct": false,
      "skipped": true
    },
    {
      "chosen": null,
      "correct": false,
      "skipped": true
    },
    {
      "chosen": null,
      "correct": false,
      "skipped": true
    },
    {
      "chosen": null,
      "correct": false,
      "skipped": true
    },
    {
      "chosen": null,
      "correct": false,
      "skipped": true
    },
    {
      "chosen": null,
      "correct": false,
      "skipped": true
    },
    {
      "chosen": null,
      "correct": false,
      "skipped": true
    },
    {
      "chosen": null,
      "correct": false,
      "skipped": true
    },
    {
      "chosen": null,
      "correct": false,
      "skipped": true
    },
    {
      "chosen": null,
      "correct": false,
      "skipped": true
    },
    {
      "chosen": null,
      "correct": false,
      "skipped": true
    },
    {
      "chosen": null,
      "correct": false,
      "skipped": true
    },
    {
      "chosen": null,
      "correct": false,
      "skipped": true
    },
    {
      "chosen": null,
      "correct": false,
      "skipped": true
    },
    {
      "chosen": null,
      "correct": false,
      "skipped": true
    },
    {
      "chosen": null,
      "correct": false,
      "skipped": true
    },
    {
      "chosen": null,
      "correct": false,
      "skipped": true
    }
  ],
  "date": "2026-05-23T22:08:47.124Z"
}