{
  "test_id": "f8a93721-6d8c-4a1e-8f2e-1c9f4d2a1b7e",
  "correct": 1,
  "total": 20,
  "answered": 1,
  "pct": 5,
  "finished": false,
  "answers": [
    {
      "chosen": null,
      "correct": false,
      "skipped": true
    },
    {
      "chosen": null,
      "correct": false,
      "skipped": true
    },
    {
      "chosen": null,
      "correct": false,
      "skipped": true
    },
    {
      "chosen": "A",
      "correct": true,
      "skipped": false
    },
    {
      "chosen": null,
      "correct": false,
      "skipped": true
    },
    {
      "chosen": null,
      "correct": false,
      "skipped": true
    },
    {
      "chosen": null,
      "correct": false,
      "skipped": true
    },
    {
      "chosen": null,
      "correct": false,
      "skipped": true
    },
    {
      "chosen": null,
      "correct": false,
      "skipped": true
    },
    {
      "chosen": null,
      "correct": false,
      "skipped": true
    },
    {
      "chosen": null,
      "correct": false,
      "skipped": true
    },
    {
      "chosen": null,
      "correct": false,
      "skipped": true
    },
    {
      "chosen": null,
      "correct": false,
      "skipped": true
    },
    {
      "chosen": null,
      "correct": false,
      "skipped": true
    },
    {
      "chosen": null,
      "correct": false,
      "skipped": true
    },
    {
      "chosen": null,
      "correct": false,
      "skipped": true
    },
    {
      "chosen": null,
      "correct": false,
      "skipped": true
    },
    {
      "chosen": null,
      "correct": false,
      "skipped": true
    },
    {
      "chosen": null,
      "correct": false,
      "skipped": true
    },
    {
      "chosen": null,
      "correct": false,
      "skipped": true
    }
  ],
  "date": "2026-04-26T16:14:45.012Z"
}